xwormclient/__init__.py
xwormclient/main.py
xwormclient-0.1.3.dist-info/METADATA
xwormclient-0.1.3.dist-info/WHEEL
xwormclient-0.1.3.dist-info/entry_points.txt
xwormclient-0.1.3.dist-info/top_level.txt
xwormclient-0.1.3.dist-info/RECORD
