Metadata-Version: 2.4
Name: xwormclient
Version: 0.1.3
Summary: مكتبة لتحميل وتشغيل ملف exe من رابط
Author: اسمك
Requires-Python: >=3.10
Dynamic: author
Dynamic: requires-python
Dynamic: summary
